circadian_scp_upload-0.5.2.dist-info/METADATA
circadian_scp_upload-0.5.2.dist-info/WHEEL
circadian_scp_upload-0.5.2.dist-info/entry_points.txt
circadian_scp_upload-0.5.2.dist-info/licenses/LICENSE
circadian_scp_upload/__init__.py
circadian_scp_upload/client.py
circadian_scp_upload/py.typed
circadian_scp_upload/screener.py
circadian_scp_upload/utils.py
circadian_scp_upload-0.5.2.dist-info/RECORD
